automl/__init__.py
automl/__version__.py
automl/automl.py
automl/automl_integration.py
automl/automl_pipeline.py
automl/hyperparameter_tuner.py
automl/metrics.py
automl/model_evaluation.py
automl/model_registry.py
automl/model_wrapper.py
automl/overfitting_handler.py
automl/preprocessors.py
automl/utils.py
automl_framework-0.1.1.dist-info/licenses/LICENSE
automl_framework-0.1.1.dist-info/METADATA
automl_framework-0.1.1.dist-info/WHEEL
automl_framework-0.1.1.dist-info/top_level.txt
automl_framework-0.1.1.dist-info/RECORD
