Metadata-Version: 2.4
Name: automl-framework
Version: 0.1.1
Summary: A comprehensive, modular framework for automated machine learning with overfitting detection and mitigation
Home-page: https://github.com/nandarizkika/automl-framework
Author: Nanda Rizkika Ruanawijaya
Author-email: Nanda Rizkika Ruanawijayae <nandarizky52@gmail.com>
Maintainer-email: Nanda Rizkika Ruanawijayae <nandarizky52@gmail.com>
License: MIT License
Project-URL: Homepage, https://github.com/nandarizkika/automl-framework
Project-URL: Documentation, https://github.com/nandarizkika/automl-framework/docs
Project-URL: Repository, https://github.com/nandarizkika/automl-framework
Project-URL: Bug Tracker, https://github.com/nandarizkika/automl-framework/issues
Project-URL: Changelog, https://github.com/nandarizkika/automl-framework/blob/main/CHANGELOG.md
Keywords: machine learning,automl,automated machine learning,overfitting,hyperparameter tuning,model selection,scikit-learn
Classifier: Development Status :: 4 - Beta
Classifier: Intended Audience :: Developers
Classifier: Intended Audience :: Science/Research
Classifier: License :: OSI Approved :: MIT License
Classifier: Operating System :: OS Independent
Classifier: Programming Language :: Python :: 3
Classifier: Programming Language :: Python :: 3.8
Classifier: Programming Language :: Python :: 3.9
Classifier: Programming Language :: Python :: 3.10
Classifier: Programming Language :: Python :: 3.11
Classifier: Topic :: Scientific/Engineering :: Artificial Intelligence
Classifier: Topic :: Software Development :: Libraries :: Python Modules
Requires-Python: >=3.8
License-File: LICENSE
Requires-Dist: numpy>=1.21.0
Requires-Dist: pandas>=1.3.0
Requires-Dist: scikit-learn>=1.0.0
Requires-Dist: matplotlib>=3.3.0
Requires-Dist: seaborn>=0.11.0
Requires-Dist: joblib>=1.0.0
Provides-Extra: dev
Requires-Dist: pytest>=6.0.0; extra == "dev"
Requires-Dist: pytest-cov>=2.12.0; extra == "dev"
Requires-Dist: black>=21.0.0; extra == "dev"
Requires-Dist: flake8>=3.9.0; extra == "dev"
Requires-Dist: isort>=5.9.0; extra == "dev"
Provides-Extra: docs
Requires-Dist: sphinx>=4.0.0; extra == "docs"
Requires-Dist: sphinx-rtd-theme>=0.5.0; extra == "docs"
Provides-Extra: jupyter
Requires-Dist: jupyter>=1.0.0; extra == "jupyter"
Requires-Dist: ipykernel>=6.0.0; extra == "jupyter"
Requires-Dist: notebook>=6.4.0; extra == "jupyter"
Provides-Extra: advanced
Requires-Dist: scikit-optimize>=0.9.0; extra == "advanced"
Requires-Dist: hyperopt>=0.2.7; extra == "advanced"
Provides-Extra: all
Requires-Dist: pytest>=6.0.0; extra == "all"
Requires-Dist: pytest-cov>=2.12.0; extra == "all"
Requires-Dist: black>=21.0.0; extra == "all"
Requires-Dist: flake8>=3.9.0; extra == "all"
Requires-Dist: isort>=5.9.0; extra == "all"
Requires-Dist: sphinx>=4.0.0; extra == "all"
Requires-Dist: sphinx-rtd-theme>=0.5.0; extra == "all"
Requires-Dist: jupyter>=1.0.0; extra == "all"
Requires-Dist: ipykernel>=6.0.0; extra == "all"
Requires-Dist: notebook>=6.4.0; extra == "all"
Requires-Dist: scikit-optimize>=0.9.0; extra == "all"
Requires-Dist: hyperopt>=0.2.7; extra == "all"
Dynamic: author
Dynamic: home-page
Dynamic: license-file
Dynamic: requires-python
